{
  "org": "vaiv",
  "last_crawled_at": "2026-07-23T20:21:51.742321+00:00",
  "models": {
    "vaiv/kobigbird-roberta-large": {
      "sha": null,
      "last_modified": null,
      "status": "active",
      "first_seen_at": "2026-07-19T13:34:19.124382+00:00",
      "last_seen_at": "2026-07-23T20:21:51.742321+00:00",
      "removed_at": null
    },
    "vaiv/GeM2-Llamion-14B-Base": {
      "sha": null,
      "last_modified": null,
      "status": "active",
      "first_seen_at": "2026-07-19T13:34:19.124382+00:00",
      "last_seen_at": "2026-07-23T20:21:51.742321+00:00",
      "removed_at": null
    },
    "vaiv/GeM2-Llamion-14B-Chat": {
      "sha": null,
      "last_modified": null,
      "status": "active",
      "first_seen_at": "2026-07-19T13:34:19.124382+00:00",
      "last_seen_at": "2026-07-23T20:21:51.742321+00:00",
      "removed_at": null
    },
    "vaiv/GeM2-Llamion-14B-LongChat": {
      "sha": null,
      "last_modified": null,
      "status": "active",
      "first_seen_at": "2026-07-19T13:34:19.124382+00:00",
      "last_seen_at": "2026-07-23T20:21:51.742321+00:00",
      "removed_at": null
    }
  }
}